firebase_dynamic_links/__init__.py
firebase_dynamic_links/__version__.py
firebase_dynamic_links/builder.py
firebase_dynamic_links/client.py
firebase_dynamic_links/dynamic_links.py
firebase_dynamic_links/errors.py
py_fdl-1.1.2.dist-info/METADATA
py_fdl-1.1.2.dist-info/RECORD
py_fdl-1.1.2.dist-info/WHEEL
py_fdl-1.1.2.dist-info/top_level.txt
