Metadata-Version: 2.1
Name: py-fdl
Version: 1.1.2
Summary: Python client for Firebase Dynamic Links
Home-page: https://github.com/heykarimoff/py-fdl
Author: Mukhammad Karimov
Author-email: hey@karimoff.me
Maintainer: Mukhammad Karimov
Maintainer-email: hey@karimoff.me
License: MIT
Project-URL: Bug Reports, https://github.com/heykarimoff/py-fdl/issues
Project-URL: Funding, https://www.karimoff.me
Project-URL: Say Thanks!, https://saythanks.io/to/heykarimoff
Project-URL: Source, https://github.com/heykarimoff/py-fdl
Keywords: firebase dynamic links super links
Platform: UNKNOWN
Classifier: Development Status :: 3 - Alpha
Classifier: Intended Audience :: Developers
Classifier: Topic :: Software Development :: Libraries :: Python Modules
Classifier: License :: OSI Approved :: MIT License
Classifier: Programming Language :: Python :: 3
Classifier: Programming Language :: Python :: 3.4
Classifier: Programming Language :: Python :: 3.5
Classifier: Programming Language :: Python :: 3.6
Provides-Extra: dev
Requires-Dist: requests
Provides-Extra: dev
Requires-Dist: pytest; extra == 'dev'
